chess_coverage/__init__.py
chess_coverage/chess_coverage.py
chess_coverage-0.1.8.dist-info/LICENSE
chess_coverage-0.1.8.dist-info/METADATA
chess_coverage-0.1.8.dist-info/WHEEL
chess_coverage-0.1.8.dist-info/top_level.txt
chess_coverage-0.1.8.dist-info/RECORD
