Metadata-Version: 2.2
Name: chess_coverage
Version: 0.1.8
Summary: Expose the potential energy of chess ply
Author-email: Gene Boggs <gene.boggs@gmail.com>
License:                     GNU GENERAL PUBLIC LICENSE
Project-URL: Homepage, https://github.com/ology/python-chess-coverage
Project-URL: Repository, https://github.com/ology/python-chess-coverage.git
Project-URL: Issues, https://github.com/ology/python-chess-coverage/issues
Classifier: Development Status :: 2 - Pre-Alpha
Classifier: Programming Language :: Python
Classifier: Programming Language :: Python :: 3
Classifier: Programming Language :: Python :: 3.9
Classifier: Programming Language :: Python :: 3.10
Classifier: Programming Language :: Python :: 3.11
Classifier: Programming Language :: Python :: 3.12
Requires-Python: >=3.9
License-File: LICENSE
Requires-Dist: chess
